20_HW/RTL_Design/Async_FIFO/rtl/async_fifo.sv
`timescale 1ns / 1ns

module async_fifo #(
    parameter DATA_WIDTH = 32,
    parameter FIFO_DEPTH = 4
) (
    input  logic                  clk_wr,
    input  logic                  rst_n_wr,
    input  logic                  wr_en,
    input  logic [DATA_WIDTH-1:0] wr_data,
    input  logic                  clk_rd,
    input  logic                  rst_n_rd,
    input  logic                  rd_en,
    output logic [DATA_WIDTH-1:0] rd_data,
    output logic                  full,
    output logic                  empty
);

    localparam PTR_WIDTH = $clog2(FIFO_DEPTH);

    logic [DATA_WIDTH-1:0] fifo_mem[0:FIFO_DEPTH-1];
    // Write and Read pointers
    logic [   PTR_WIDTH:0] wr_ptr;
    logic [   PTR_WIDTH:0] rd_ptr;
    // Gray code pointers
    logic [   PTR_WIDTH:0] wr_ptr_gray;
    logic [   PTR_WIDTH:0] rd_ptr_gray;
    // rd_clk domain pointers
    logic [   PTR_WIDTH:0] wr_ptr_gray_sync_0;
    logic [   PTR_WIDTH:0] wr_ptr_gray_sync_1;
    // wr_clk domain pointers
    logic [   PTR_WIDTH:0] rd_ptr_gray_sync_0;
    logic [   PTR_WIDTH:0] rd_ptr_gray_sync_1;

    // Write operation
    always_ff @(posedge clk_wr, negedge rst_n_wr) begin
        if (!rst_n_wr) begin
            wr_ptr <= 0;
            wr_ptr_gray <= 0;
        end else if (wr_en && !full) begin
            fifo_mem[wr_ptr[PTR_WIDTH-1:0]] <= wr_data;
            wr_ptr <= wr_ptr + 1;
            wr_ptr_gray <= (wr_ptr + 1) ^ ((wr_ptr + 1) >> 1); // Convert to Gray code
        end
    end

    // Read operation
    always_ff @(posedge clk_rd, negedge rst_n_rd) begin
        if (!rst_n_rd) begin
            rd_ptr <= 0;
            rd_ptr_gray <= 0;
        end else if (rd_en && !empty) begin
            rd_data <= fifo_mem[rd_ptr[PTR_WIDTH-1:0]];
            rd_ptr <= rd_ptr + 1;
            rd_ptr_gray <= (rd_ptr + 1) ^ ((rd_ptr + 1) >> 1); // Convert to Gray code
        end
    end

    // 2-stage Synchronizer
    always_ff @(posedge clk_rd, negedge rst_n_rd) begin
        if (!rst_n_rd) begin
            wr_ptr_gray_sync_0 <= 0;
            wr_ptr_gray_sync_1 <= 0;
        end else begin
            wr_ptr_gray_sync_0 <= wr_ptr_gray;
            wr_ptr_gray_sync_1 <= wr_ptr_gray_sync_0;
        end
    end

    always_ff @(posedge clk_wr, negedge rst_n_wr) begin
        if (!rst_n_wr) begin
            rd_ptr_gray_sync_0 <= 0;
            rd_ptr_gray_sync_1 <= 0;
        end else begin
            rd_ptr_gray_sync_0 <= rd_ptr_gray;
            rd_ptr_gray_sync_1 <= rd_ptr_gray_sync_0;
        end
    end

    // full and empty flags
    assign empty = (wr_ptr_gray_sync_1 == rd_ptr_gray);
    assign full  = (wr_ptr_gray == {~rd_ptr_gray_sync_1[PTR_WIDTH:PTR_WIDTH-1], rd_ptr_gray_sync_1[PTR_WIDTH-2:0]});

endmodule

20_HW/RTL_Design/Async_FIFO/tb/tb_async_fifo.sv
`timescale 1ns / 1ps

module tb_async_fifo;
    // Parameters & Signals
    localparam DATA_WIDTH = 32;
    localparam FIFO_DEPTH = 4;

    logic                  clk_wr;
    logic                  rst_n_wr;
    logic                  wr_en;
    logic [DATA_WIDTH-1:0] wr_data;
    logic                  clk_rd;
    logic                  rst_n_rd;
    logic                  rd_en;
    logic [DATA_WIDTH-1:0] rd_data;
    logic                  full;
    logic                  empty;

    // DUT Instance
    async_fifo #(
        .DATA_WIDTH(DATA_WIDTH),
        .FIFO_DEPTH(FIFO_DEPTH)
    ) dut (
        .clk_wr  (clk_wr),
        .rst_n_wr(rst_n_wr),
        .wr_en   (wr_en),
        .wr_data (wr_data),
        .clk_rd  (clk_rd),
        .rst_n_rd(rst_n_rd),
        .rd_en   (rd_en),
        .rd_data (rd_data),
        .full    (full),
        .empty   (empty)
    );

    // 100MHZ WriteClock Generation
    initial begin
        clk_wr = 0;
        forever #5 clk_wr = ~clk_wr;
    end

    // 200MHz ReadClock Generation
    initial begin
        clk_rd = 0;
        forever #2.5 clk_rd = ~clk_rd;
    end

    integer fd_in;  // stimulus inputs
    integer fd_out;  // DUT outputs (for debugging)
    string cmd;
    logic [DATA_WIDTH-1:0] data;

    // Test Sequence
    initial begin
        // Dumpfile
        $dumpfile("tb_async_fifo.vcd");
        $dumpvars(0, tb_async_fifo);

        // Reset
        rst_n_wr = 0;
        rst_n_rd = 0;
        wr_en = 0;
        rd_en = 0;
        wr_data = 0;

        // Reset timeng 맞추기 위해 fork-join 사용
        fork
            // Write Clock Reset
            begin
                @(posedge clk_wr);
                #1;
                rst_n_wr = 1;
            end
            // Read Clock Reset
            begin
                @(posedge clk_rd);
                #1;
                rst_n_rd = 1;
            end
        join

        // Open stimulus file
        fd_in  = $fopen("./model/stimulus.txt", "r");
        fd_out = $fopen("./model/dut_output.txt", "w");

        if (fd_in == 0 || fd_out == 0) begin
            $display("Failed to open files.");
            $finish;
        end

        while (!$feof(
            fd_in
        )) begin
            // 파일에서 한 줄 읽기
            $fscanf(fd_in, "%s %d\n", cmd, data);

            if (cmd == "WRITE") begin
                // Task를 활용하여 clk_wr 도메인으로 안전하게 인가
                fifo_write(data);
            end else if (cmd == "READ") begin
                // Task를 활용하여 clk_rd 도메인으로 안전하게 인가
                fifo_read();
            end
        end

        $fclose(fd_in);
        $fclose(fd_out);
        #100;  // wait
        $display("Test Completed.");
        $display("dut_output.txt generated.");

        $finish;
    end

    // Monitor DUT outputs (for debugging)
    always @(posedge clk_wr) begin
        if (rst_n_wr && wr_en && !full) begin
            #1;  // wr_data가 data에 반영될 시간
            $fdisplay(
                fd_out,
                "WRITE: data=%0d, wr_ptr=%0d, rd_ptr=%0d, full=%0b, empty=%0b",
                wr_data, dut.wr_ptr, dut.rd_ptr, full, empty);
        end else if (rst_n_wr && wr_en && full) begin
            $fdisplay(fd_out, "WRITE FAIL (full): data=%0d", wr_data);
        end
    end

    always @(posedge clk_rd) begin
        if (rst_n_rd && rd_en && !empty) begin
            #1;  // Data가 rd_data에 반영될 시간
            $fdisplay(
                fd_out,
                "READ: data=%0d, wr_ptr=%0d, rd_ptr=%0d, full=%0b, empty=%0b",
                rd_data, dut.wr_ptr, dut.rd_ptr, full, empty);
        end else if (rst_n_rd && rd_en && empty) begin
            $fdisplay(fd_out, "READ FAIL (empty)");
        end
    end

    // Verification Tasks
    task fifo_write(input logic [DATA_WIDTH-1:0] data);
        begin
            @(posedge clk_wr);
            #1;  // Setup Time
            wr_en   = 1;
            wr_data = data;
            @(posedge clk_wr);
            #1;  // Hold Time
            wr_en   = 0;
            wr_data = 0;
        end
    endtask

    task fifo_read();
        begin
            @(posedge clk_rd);
            #1;  // Setup Time
            rd_en = 1;
            @(posedge clk_rd);
            #1;  // Hold Time
            rd_en = 0;
        end
    endtask

endmodule

20_HW/RTL_Design/Async_FIFO/tb_async_fifo.vcd
$date
	Wed Jun  3 17:48:05 2026
$end
$version
	Icarus Verilog
$end
$timescale
	1ps
$end
$scope module tb_async_fifo $end
$var wire 32 ! rd_data [31:0] $end
$var wire 1 " full $end
$var wire 1 # empty $end
$var parameter 32 $ DATA_WIDTH $end
$var parameter 32 % FIFO_DEPTH $end
$var reg 1 & clk_rd $end
$var reg 1 ' clk_wr $end
$var reg 32 ( data [31:0] $end
$var reg 1 ) rd_en $end
$var reg 1 * rst_n_rd $end
$var reg 1 + rst_n_wr $end
$var reg 32 , wr_data [31:0] $end
$var reg 1 - wr_en $end
$var integer 32 . fd_in [31:0] $end
$var integer 32 / fd_out [31:0] $end
$scope module dut $end
$var wire 1 & clk_rd $end
$var wire 1 ' clk_wr $end
$var wire 1 ) rd_en $end
$var wire 1 * rst_n_rd $end
$var wire 1 + rst_n_wr $end
$var wire 32 0 wr_data [31:0] $end
$var wire 1 - wr_en $end
$var wire 1 " full $end
$var wire 1 # empty $end
$var parameter 32 1 DATA_WIDTH $end
$var parameter 32 2 FIFO_DEPTH $end
$var parameter 32 3 PTR_WIDTH $end
$var reg 32 4 rd_data [31:0] $end
$var reg 3 5 rd_ptr [2:0] $end
$var reg 3 6 rd_ptr_gray [2:0] $end
$var reg 3 7 rd_ptr_gray_sync_0 [2:0] $end
$var reg 3 8 rd_ptr_gray_sync_1 [2:0] $end
$var reg 3 9 wr_ptr [2:0] $end
$var reg 3 : wr_ptr_gray [2:0] $end
$var reg 3 ; wr_ptr_gray_sync_0 [2:0] $end
$var reg 3 < wr_ptr_gray_sync_1 [2:0] $end
$upscope $end
$scope task fifo_read $end
$upscope $end
$scope task fifo_write $end
$var reg 32 = data [31:0] $end
$upscope $end
$upscope $end
$enddefinitions $end
$comment Show the parameter values. $end
$dumpall
b10 3
b100 2
b100000 1
b100 %
b100000 $
$end
#0
$dumpvars
bx =
b0 <
b0 ;
b0 :
b0 9
b0 8
b0 7
b0 6
b0 5
bx 4
b0 0
bx /
bx .
0-
b0 ,
0+
0*
0)
bx (
0'
0&
1#
0"
bx !
$end
#2500
1&
#3500
1*
#5000
0&
1'
#6000
b10000000000000000000000000000100 /
b10000000000000000000000000000011 .
1+
#7500
1&
#8500
1)
#10000
0&
0'
#12500
1&
#13500
0)
#15000
0&
1'
#17500
1&
#18500
1)
#20000
0&
0'
#22500
1&
#23500
0)
#25000
0&
1'
#27500
1&
#28500
1)
#30000
0&
0'
#32500
1&
#33500
b101100 =
b101100 (
0)
#35000
0&
1'
#36000
b101100 ,
b101100 0
1-
#37500
1&
#40000
0&
0'
#42500
1&
#45000
b1 :
b1 9
0&
1'
#46000
b0 ,
b0 0
0-
#47500
b1 ;
1&
#48500
1)
#50000
0&
0'
#52500
0#
b1 <
1&
#53500
0)
#55000
0&
1'
#57500
1&
#58500
1)
#60000
0&
0'
#62500
1#
b1 6
b1 5
b101100 !
b101100 4
1&
#63500
0)
#65000
b1 7
0&
1'
#67500
1&
#68500
1)
#70000
0&
0'
#72500
1&
#73500
b11001 =
b11001 (
0)
#75000
b1 8
0&
1'
#76000
b11001 ,
b11001 0
1-
#77500
1&
#80000
0&
0'
#82500
1&
#85000
b11 :
b10 9
0&
1'
#86000
b1100 =
b1100 (
b0 ,
b0 0
0-
#87500
b11 ;
1&
#90000
0&
0'
#92500
0#
b11 <
1&
#95000
0&
1'
#96000
b1100 ,
b1100 0
1-
#97500
1&
#100000
0&
0'
#102500
1&
#105000
b10 :
b11 9
0&
1'
#106000
b0 ,
b0 0
0-
#107500
b10 ;
1&
#108500
1)
#110000
0&
0'
#112500
b10 <
0#
b11 6
b10 5
b11001 !
b11001 4
1&
#113500
0)
#115000
b11 7
0&
1'
#117500
1&
#118500
1)
#120000
0&
0'
#122500
1#
b10 6
b11 5
b1100 !
b1100 4
1&
#123500
b111 =
b111 (
0)
#125000
b11 8
b10 7
0&
1'
#126000
b111 ,
b111 0
1-
#127500
1&
#130000
0&
0'
#132500
1&
#135000
b110 :
b100 9
b10 8
0&
1'
#136000
b101000 =
b101000 (
b0 ,
b0 0
0-
#137500
b110 ;
1&
#140000
0&
0'
#142500
0#
b110 <
1&
#145000
0&
1'
#146000
b101000 ,
b101000 0
1-
#147500
1&
#150000
0&
0'
#152500
1&
#155000
b111 :
b101 9
0&
1'
#156000
b1011011 =
b1011011 (
b0 ,
b0 0
0-
#157500
b111 ;
1&
#160000
0&
0'
#162500
b111 <
1&
#165000
0&
1'
#166000
b1011011 ,
b1011011 0
1-
#167500
1&
#170000
0&
0'
#172500
1&
#175000
b101 :
b110 9
0&
1'
#176000
b0 ,
b0 0
0-
#177500
b101 ;
1&
#178500
1)
#180000
0&
0'
#182500
b101 <
b110 6
b100 5
b111 !
b111 4
1&
#183500
b1100001 =
b1100001 (
0)
#185000
b110 7
0&
1'
#186000
b1100001 ,
b1100001 0
1-
#187500
1&
#190000
0&
0'
#192500
1&
#195000
0"
b100 :
b111 9
b110 8
0&
1'
#196000
b101101 =
b101101 (
b0 ,
b0 0
0-
#197500
b100 ;
1&
#200000
0&
0'
#202500
b100 <
1&
#205000
0&
1'
#206000
b101101 ,
b101101 0
1-
#207500
1&
#210000
0&
0'
#212500
1&
#215000
b0 9
0&
1'
#216000
b101111 =
b101111 (
b0 ,
b0 0
0-
#217500
1&
#220000
0&
0'
#222500
1&
#225000
0&
1'
#226000
b101111 ,
b101111 0
1-
#227500
1&
#230000
0&
0'
#232500
1&
#235000
b1 :
b1 9
0&
1'
#236000
b0 ,
b0 0
0-
#237500
b1 ;
1&
#238500
1)
#240000
0&
0'
#242500
b1 <
b111 6
b101 5
b101111 !
b101111 4
1&
#243500
0)
#245000
b111 7
0&
1'
#247500
1&
#248500
1)
#250000
0&
0'
#252500
b101 6
b110 5
b1011011 !
b1011011 4
1&
#253500
0)
#255000
1"
b111 8
b101 7
0&
1'
#257500
1&
#260000
0&
0'
#262500
1&
#265000
0"
b101 8
0&
1'
