20_HW/RTL_Design/Async_FIFO/rtl/async_fifo.sv
module async_fifo #(
    parameter DATA_WIDTH = 32,
    parameter FIFO_DEPTH = 4
) (
    input  logic                  clk_wr,
    input  logic                  rst_n_wr,
    input  logic                  wr_en,
    input  logic [DATA_WIDTH-1:0] wr_data,
    input  logic                  clk_rd,
    input  logic                  rst_n_rd,
    input  logic                  rd_en,
    output logic [DATA_WIDTH-1:0] rd_data,
    output logic                  full,
    output logic                  empty
);

    localparam PTR_WIDTH = $clog2(FIFO_DEPTH);

    logic [DATA_WIDTH-1:0] fifo_mem[0:FIFO_DEPTH-1];
    // Write and Read pointers
    logic [   PTR_WIDTH:0] wr_ptr;
    logic [   PTR_WIDTH:0] rd_ptr;
    // Write and Read next pointers
    logic [   PTR_WIDTH:0] wr_ptr_next;
    logic [   PTR_WIDTH:0] rd_ptr_next;
    // Gray code pointers
    logic [   PTR_WIDTH:0] wr_ptr_gray;
    logic [   PTR_WIDTH:0] rd_ptr_gray;
    // rd_clk domain pointers
    logic [   PTR_WIDTH:0] wr_ptr_gray_sync_0;
    logic [   PTR_WIDTH:0] wr_ptr_gray_sync_1;
    // wr_clk domain pointers
    logic [   PTR_WIDTH:0] rd_ptr_gray_sync_0;
    logic [   PTR_WIDTH:0] rd_ptr_gray_sync_1;

    // Write operation
    assign wr_ptr_next = wr_ptr + 1;

    always_ff @(posedge clk_wr, negedge rst_n_wr) begin
        if (!rst_n_wr) begin
            wr_ptr      <= 0;
            wr_ptr_gray <= 0;
        end else if (wr_en && !full) begin
            fifo_mem[wr_ptr[PTR_WIDTH-1:0]] <= wr_data;
            wr_ptr      <= wr_ptr_next;
            wr_ptr_gray <= (wr_ptr_next) ^ ((wr_ptr_next) >> 1); // Convert to Gray code
        end
    end

    // Read operation
    assign rd_ptr_next = rd_ptr + 1;

    always_ff @(posedge clk_rd, negedge rst_n_rd) begin
        if (!rst_n_rd) begin
            rd_ptr      <= 0;
            rd_ptr_gray <= 0;
        end else if (rd_en && !empty) begin
            rd_ptr      <= rd_ptr_next;
            rd_ptr_gray <= (rd_ptr_next) ^ ((rd_ptr_next) >> 1); // Convert to Gray code
        end
    end

    // 2-stage Synchronizer
    always_ff @(posedge clk_rd, negedge rst_n_rd) begin
        if (!rst_n_rd) begin
            wr_ptr_gray_sync_0 <= 0;
            wr_ptr_gray_sync_1 <= 0;
        end else begin
            wr_ptr_gray_sync_0 <= wr_ptr_gray;
            wr_ptr_gray_sync_1 <= wr_ptr_gray_sync_0;
        end
    end

    always_ff @(posedge clk_wr, negedge rst_n_wr) begin
        if (!rst_n_wr) begin
            rd_ptr_gray_sync_0 <= 0;
            rd_ptr_gray_sync_1 <= 0;
        end else begin
            rd_ptr_gray_sync_0 <= rd_ptr_gray;
            rd_ptr_gray_sync_1 <= rd_ptr_gray_sync_0;
        end
    end

    // Write Pointer Nexy Value - FULL 인식이 느려 타이밍 맞춤
    // logic [PTR_WIDTH:0] wr_ptr_gray_next;
    // assign wr_ptr_gray_next = (wr_ptr + 1) ^ ((wr_ptr + 1) >> 1);

    // full and empty flags
    assign empty = (rd_ptr_gray == wr_ptr_gray_sync_1);
    // assign full  = (wr_ptr_gray_next == {~rd_ptr_gray_sync_1[PTR_WIDTH:PTR_WIDTH-1], rd_ptr_gray_sync_1[PTR_WIDTH-2:0]});
    assign full  = (wr_ptr_gray == {~rd_ptr_gray_sync_1[PTR_WIDTH:PTR_WIDTH-1], rd_ptr_gray_sync_1[PTR_WIDTH-2:0]});

    // output data
    assign rd_data = fifo_mem[rd_ptr[PTR_WIDTH-1:0]];

endmodule

20_HW/RTL_Design/Async_FIFO/tb/tb_async_fifo.sv
`timescale 1ns / 1ps

module tb_async_fifo;
    // Parameters & Signals
`ifdef DATA_WIDTH_DEF
    localparam DATA_WIDTH = `DATA_WIDTH_DEF;
`else
    localparam DATA_WIDTH = 32;
`endif

`ifdef FIFO_DEPTH_DEF
    localparam FIFO_DEPTH = `FIFO_DEPTH_DEF;
`else
    localparam FIFO_DEPTH = 4;
`endif

    logic                  clk_wr;
    logic                  rst_n_wr;
    logic                  wr_en;
    logic [DATA_WIDTH-1:0] wr_data;
    logic                  clk_rd;
    logic                  rst_n_rd;
    logic                  rd_en;
    logic [DATA_WIDTH-1:0] rd_data;
    logic                  full;
    logic                  empty;

    // DUT Instance
    async_fifo #(
        .DATA_WIDTH(DATA_WIDTH),
        .FIFO_DEPTH(FIFO_DEPTH)
    ) dut (
        .clk_wr  (clk_wr),
        .rst_n_wr(rst_n_wr),
        .wr_en   (wr_en),
        .wr_data (wr_data),
        .clk_rd  (clk_rd),
        .rst_n_rd(rst_n_rd),
        .rd_en   (rd_en),
        .rd_data (rd_data),
        .full    (full),
        .empty   (empty)
    );

    // 200MHZ WriteClock Generation
    initial begin
        clk_wr = 0;
        forever #2.5 clk_wr = ~clk_wr;
    end

    // 100MHz ReadClock Generation
    initial begin
        clk_rd = 0;
        forever #5 clk_rd = ~clk_rd;
    end

    integer fd_in;  // stimulus inputs
    integer fd_out;  // DUT outputs (for debugging)
    string cmd;
    logic [DATA_WIDTH-1:0] data;

    // Test Sequence
    initial begin
        // Dumpfile
        $dumpfile("./sim/wave.vcd");
        $dumpvars(0, tb_async_fifo);

        // Reset
        rst_n_wr = 0;
        rst_n_rd = 0;
        wr_en = 0;
        rd_en = 0;
        wr_data = 0;

        // Reset timeng 맞추기 위해 fork-join 사용
        fork
            // Write Clock Reset
            begin
                @(posedge clk_wr);
                #1;
                rst_n_wr = 1;
            end
            // Read Clock Reset
            begin
                @(posedge clk_rd);
                #1;
                rst_n_rd = 1;
            end
        join

        // Open stimulus file
        fd_in  = $fopen("./sim/stimulus.txt", "r");
        fd_out = $fopen("./sim/dut_output.txt", "w");

        if (fd_in == 0 || fd_out == 0) begin
            $display("Failed to open files.");
            $finish;
        end

        while (!$feof(
            fd_in
        )) begin
            // 파일에서 한 줄 읽기
            $fscanf(fd_in, "%s %d\n", cmd, data);

            if (cmd == "WRITE") begin
                // Task를 활용하여 clk_wr 도메인으로 안전하게 인가
                fifo_write(data);
            end else if (cmd == "READ") begin
                // Task를 활용하여 clk_rd 도메인으로 안전하게 인가
                fifo_read();
            end else if (cmd == "WAIT") begin
                @(negedge full);
                @(posedge clk_wr);
            end
        end

        $fclose(fd_in);
        $fclose(fd_out);
        #100;  // wait
        $display("Test Completed.");
        $display("dut_output.txt generated.");

        $finish;
    end

    // Write Monitor
    always @(posedge clk_wr) begin
        if (rst_n_wr && wr_en && !full) begin
            $fdisplay(fd_out, "WRITE: data=%0d @ %0t", wr_data, $time);
        end else if (rst_n_wr && wr_en && full) begin
            $fdisplay(fd_out, "WRITE FAIL (full): data=%0d @ %0t", wr_data,
                      $time);
        end
    end

    // Read Monitor
    always @(posedge clk_rd) begin
        if (rst_n_rd && rd_en && !empty) begin
            $fdisplay(fd_out, "READ : data=%0d @ %0t", rd_data, $time);
        end else if (rst_n_rd && rd_en && empty) begin
            $fdisplay(fd_out, "READ FAIL (empty): @ %0t", $time);
        end
    end

    // Verification Tasks
    task fifo_write(input logic [DATA_WIDTH-1:0] data);
        begin
            @(posedge clk_wr);
            #1;  // Setup Time
            wr_en   = 1;
            wr_data = data;
            @(posedge clk_wr);
            #1;  // Hold Time
            wr_en = 0;
        end
    endtask

    task fifo_read();
        begin
            @(posedge clk_rd);
            #1;  // Setup Time
            rd_en = 1;
            @(posedge clk_rd);
            #1;  // Hold Time
            rd_en = 0;
        end
    endtask

endmodule

20_HW/RTL_Design/Async_FIFO/sim/wave.vcd
$date
	Thu Jun 04 16:47:26 2026
$end
$version
	Icarus Verilog
$end
$timescale
	1ps
$end
$scope module tb_async_fifo $end
$var wire 32 ! rd_data [31:0] $end
$var wire 1 " full $end
$var wire 1 # empty $end
$var parameter 32 $ DATA_WIDTH $end
$var parameter 32 % FIFO_DEPTH $end
$var reg 1 & clk_rd $end
$var reg 1 ' clk_wr $end
$var reg 32 ( data [31:0] $end
$var reg 1 ) rd_en $end
$var reg 1 * rst_n_rd $end
$var reg 1 + rst_n_wr $end
$var reg 32 , wr_data [31:0] $end
$var reg 1 - wr_en $end
$var integer 32 . fd_in [31:0] $end
$var integer 32 / fd_out [31:0] $end
$scope module dut $end
$var wire 1 & clk_rd $end
$var wire 1 ' clk_wr $end
$var wire 32 0 rd_data [31:0] $end
$var wire 1 ) rd_en $end
$var wire 1 * rst_n_rd $end
$var wire 1 + rst_n_wr $end
$var wire 32 1 wr_data [31:0] $end
$var wire 1 - wr_en $end
$var wire 3 2 wr_ptr_next [2:0] $end
$var wire 3 3 rd_ptr_next [2:0] $end
$var wire 1 " full $end
$var wire 1 # empty $end
$var parameter 32 4 DATA_WIDTH $end
$var parameter 32 5 FIFO_DEPTH $end
$var parameter 32 6 PTR_WIDTH $end
$var reg 3 7 rd_ptr [2:0] $end
$var reg 3 8 rd_ptr_gray [2:0] $end
$var reg 3 9 rd_ptr_gray_sync_0 [2:0] $end
$var reg 3 : rd_ptr_gray_sync_1 [2:0] $end
$var reg 3 ; wr_ptr [2:0] $end
$var reg 3 < wr_ptr_gray [2:0] $end
$var reg 3 = wr_ptr_gray_sync_0 [2:0] $end
$var reg 3 > wr_ptr_gray_sync_1 [2:0] $end
$upscope $end
$scope task fifo_read $end
$upscope $end
$scope task fifo_write $end
$var reg 32 ? data [31:0] $end
$upscope $end
$upscope $end
$enddefinitions $end
$comment Show the parameter values. $end
$dumpall
b10 6
b100 5
b100000 4
b100 %
b100000 $
$end
#0
$dumpvars
bx ?
b0 >
b0 =
b0 <
b0 ;
b0 :
b0 9
b0 8
b0 7
b1 3
b1 2
b0 1
bx 0
bx /
bx .
0-
b0 ,
0+
0*
0)
bx (
0'
0&
1#
0"
bx !
$end
#2500
1'
#3500
1+
#5000
0'
1&
#6000
b10000000000000000000000000000100 /
b10000000000000000000000000000011 .
1*
#7500
1'
#10000
0'
0&
#12500
1'
#15000
0'
1&
#16000
1)
#17500
1'
#20000
0'
0&
#22500
1'
#25000
0'
1&
#26000
0)
#27500
1'
#30000
0'
0&
#32500
1'
#35000
0'
1&
#36000
1)
#37500
1'
#40000
0'
0&
#42500
1'
#45000
0'
1&
#46000
0)
#47500
1'
#50000
0'
0&
#52500
1'
#55000
0'
1&
#56000
1)
#57500
1'
#60000
0'
0&
#62500
1'
#65000
0'
1&
#66000
b101100 ?
b101100 (
0)
#67500
1'
#68500
b101100 ,
b101100 1
1-
#70000
0'
0&
#72500
b1 <
b10 2
b1 ;
b101100 !
b101100 0
1'
#73500
0-
#75000
b1 =
0'
1&
#76000
1)
#77500
1'
#80000
0'
0&
#82500
1'
#85000
0#
b1 >
0'
1&
#86000
0)
#87500
1'
#90000
0'
0&
#92500
1'
#95000
0'
1&
#96000
1)
#97500
1'
#100000
0'
0&
#102500
1'
#105000
bx !
bx 0
1#
b1 8
b10 3
b1 7
0'
1&
#106000
0)
#107500
b1 9
1'
#110000
0'
0&
#112500
b1 :
1'
#115000
0'
1&
#116000
1)
#117500
1'
#120000
0'
0&
#122500
1'
#125000
0'
1&
#126000
b11001 ?
b11001 (
0)
#127500
1'
#128500
b11001 ,
b11001 1
1-
#130000
0'
0&
#132500
b11 <
b11 2
b10 ;
b11001 !
b11001 0
1'
#133500
b1100 ?
b1100 (
0-
#135000
b11 =
0'
1&
#137500
1'
#138500
b1100 ,
b1100 1
1-
#140000
0'
0&
#142500
b10 <
b100 2
b11 ;
1'
#143500
0-
#145000
0#
b11 >
b10 =
0'
1&
#146000
1)
#147500
1'
#150000
0'
0&
#152500
1'
#155000
b1100 !
b1100 0
b11 8
b11 3
b10 7
b10 >
0'
1&
#156000
0)
#157500
b11 9
1'
#160000
0'
0&
#162500
b11 :
1'
#165000
0'
1&
#166000
1)
#167500
1'
#170000
0'
0&
#172500
1'
#175000
bx !
bx 0
1#
b10 8
b100 3
b11 7
0'
1&
#176000
b111 ?
b111 (
0)
#177500
b10 9
1'
#178500
b111 ,
b111 1
1-
#180000
0'
0&
#182500
b10 :
b110 <
b101 2
b100 ;
b111 !
b111 0
1'
#183500
b101000 ?
b101000 (
0-
#185000
b110 =
0'
1&
#187500
1'
#188500
b101000 ,
b101000 1
1-
#190000
0'
0&
#192500
b111 <
b110 2
b101 ;
1'
#193500
b1011011 ?
b1011011 (
0-
#195000
0#
b110 >
b111 =
0'
1&
#197500
1'
#198500
b1011011 ,
b1011011 1
1-
#200000
0'
0&
#202500
b101 <
b111 2
b110 ;
1'
#203500
0-
#205000
b111 >
b101 =
0'
1&
#206000
1)
#207500
1'
#210000
0'
0&
#212500
1'
#215000
b101000 !
b101000 0
b110 8
b101 3
b100 7
b101 >
0'
1&
#216000
b1100001 ?
b1100001 (
0)
#217500
b110 9
1'
#218500
b1100001 ,
b1100001 1
1-
#220000
0'
0&
#222500
b110 :
0"
b100 <
b0 2
b111 ;
1'
#223500
b101101 ?
b101101 (
0-
#225000
b100 =
0'
1&
#227500
1'
#228500
b101101 ,
b101101 1
1-
#230000
0'
0&
#232500
1"
b0 <
b1 2
b0 ;
1'
#233500
b101111 ?
b101111 (
0-
#235000
b100 >
b0 =
0'
1&
#237500
1'
#238500
b101111 ,
b101111 1
1-
#240000
0'
0&
#242500
1'
#243500
0-
#245000
b0 >
0'
1&
#246000
1)
#247500
1'
#250000
0'
0&
#252500
1'
#255000
b1011011 !
b1011011 0
b111 8
b110 3
b101 7
0'
1&
#256000
0)
#257500
b111 9
1'
#260000
0'
0&
#262500
0"
b111 :
1'
#265000
0'
1&
#267500
1'
#270000
0'
0&
#272500
1'
#275000
0'
1&
#276000
1)
#277500
1'
#280000
0'
0&
#282500
1'
#285000
b1100001 !
b1100001 0
b101 8
b111 3
b110 7
0'
1&
#286000
0)
#287500
b101 9
1'
#290000
0'
0&
#292500
b101 :
1'
#295000
0'
1&
#296000
1)
#297500
1'
#300000
0'
0&
#302500
1'
#305000
b101101 !
b101101 0
b100 8
b0 3
b111 7
0'
1&
#306000
0)
#307500
b100 9
1'
#310000
0'
0&
#312500
b100 :
1'
#315000
0'
1&
#316000
1)
#317500
1'
#320000
0'
0&
#322500
1'
#325000
b101000 !
b101000 0
1#
b0 8
b1 3
b0 7
0'
1&
#326000
b1100011 ?
b1100011 (
0)
#327500
b0 9
1'
#328500
b1100011 ,
b1100011 1
1-
#330000
0'
0&
#332500
b0 :
b1 <
b10 2
b1 ;
b1100011 !
b1100011 0
1'
#333500
0-
#335000
b1 =
0'
1&
#336000
1)
#337500
1'
#340000
0'
0&
#342500
1'
#345000
0#
b1 >
0'
1&
#346000
0)
#347500
1'
#350000
0'
0&
#352500
1'
#355000
0'
1&
#356000
1)
#357500
1'
#360000
0'
0&
#362500
1'
#365000
b1011011 !
b1011011 0
1#
b1 8
b10 3
b1 7
0'
1&
#366000
b10111 ?
b10111 (
0)
#367500
b1 9
1'
#368500
b10111 ,
b10111 1
1-
#370000
0'
0&
#372500
b1 :
b11 <
b11 2
b10 ;
b10111 !
b10111 0
1'
#373500
0-
#375000
b11 =
0'
1&
#376000
1)
#377500
1'
#380000
0'
0&
#382500
1'
#385000
0#
b11 >
0'
1&
#386000
0)
#387500
1'
#390000
0'
0&
#392500
1'
#395000
0'
1&
#396000
1)
#397500
1'
#400000
0'
0&
#402500
1'
#405000
b1100001 !
b1100001 0
1#
b11 8
b11 3
b10 7
0'
1&
#406000
0)
#407500
b11 9
1'
#410000
0'
0&
#412500
b11 :
1'
#415000
0'
1&
#416000
1)
#417500
1'
#420000
0'
0&
#422500
1'
#425000
0'
1&
#426000
0)
#427500
1'
#430000
0'
0&
#432500
1'
#435000
0'
1&
#436000
1)
#437500
1'
#440000
0'
0&
#442500
1'
#445000
0'
1&
#446000
b100011 ?
b100011 (
0)
#447500
1'
#448500
b100011 ,
b100011 1
1-
#450000
0'
0&
#452500
b10 <
b100 2
b11 ;
b100011 !
b100011 0
1'
#453500
b1000111 ?
b1000111 (
0-
#455000
b10 =
0'
1&
#457500
1'
#458500
b1000111 ,
b1000111 1
1-
#460000
0'
0&
#462500
b110 <
b101 2
b100 ;
1'
#463500
b1010110 ?
b1010110 (
0-
#465000
0#
b10 >
b110 =
0'
1&
#467500
1'
#468500
b1010110 ,
b1010110 1
1-
#470000
0'
0&
#472500
b111 <
b110 2
b101 ;
1'
#473500
0-
#475000
b110 >
b111 =
0'
1&
#476000
1)
#477500
1'
#480000
0'
0&
#482500
1'
#485000
b1000111 !
b1000111 0
b111 >
b10 8
b100 3
b11 7
0'
1&
#486000
0)
#487500
b10 9
1'
#490000
0'
0&
#492500
b10 :
1'
#495000
0'
1&
#496000
1)
#497500
1'
#500000
0'
0&
#502500
1'
#505000
b1010110 !
b1010110 0
b110 8
b101 3
b100 7
0'
1&
#506000
b1001100 ?
b1001100 (
0)
#507500
b110 9
1'
#508500
b1001100 ,
b1001100 1
1-
#510000
0'
0&
#512500
b110 :
b101 <
b111 2
b110 ;
1'
#513500
0-
#515000
b101 =
0'
1&
#516000
1)
#517500
1'
#520000
0'
0&
#522500
1'
#525000
b1001100 !
b1001100 0
b101 >
0#
b111 8
b110 3
b101 7
0'
1&
#526000
0)
#527500
b111 9
1'
#530000
0'
0&
#532500
b111 :
1'
#535000
0'
1&
#536000
1)
#537500
1'
#540000
0'
0&
#542500
1'
#545000
b100011 !
b100011 0
1#
b101 8
b111 3
b110 7
0'
1&
#546000
0)
#547500
b101 9
1'
#550000
0'
0&
#552500
b101 :
1'
#555000
0'
1&
#556000
1)
#557500
1'
#560000
0'
0&
#562500
1'
#565000
0'
1&
#566000
b1001111 ?
b1001111 (
0)
#567500
1'
#568500
b1001111 ,
b1001111 1
1-
#570000
0'
0&
#572500
b100 <
b0 2
b111 ;
b1001111 !
b1001111 0
1'
#573500
b10111 ?
b10111 (
0-
#575000
b100 =
0'
1&
#577500
1'
#578500
b10111 ,
b10111 1
1-
#580000
0'
0&
#582500
b0 <
b1 2
b0 ;
1'
#583500
0-
#585000
0#
b100 >
b0 =
0'
1&
#586000
1)
#587500
1'
#590000
0'
0&
#592500
1'
#595000
b10111 !
b10111 0
b100 8
b0 3
b111 7
b0 >
0'
1&
#596000
b111010 ?
b111010 (
0)
#597500
b100 9
1'
#598500
b111010 ,
b111010 1
1-
#600000
0'
0&
#602500
b100 :
b1 <
b10 2
b1 ;
1'
#603500
0-
#605000
b1 =
0'
1&
#606000
1)
#607500
1'
#610000
0'
0&
#612500
1'
#615000
b111010 !
b111010 0
b0 8
b1 3
b0 7
b1 >
0'
1&
#616000
b100001 ?
b100001 (
0)
#617500
b0 9
1'
#618500
b100001 ,
b100001 1
1-
#620000
0'
0&
#622500
b0 :
b11 <
b11 2
b10 ;
1'
#623500
b1000011 ?
b1000011 (
0-
#625000
b11 =
0'
1&
#627500
1'
#628500
b1000011 ,
b1000011 1
1-
#630000
0'
0&
#632500
b10 <
b100 2
b11 ;
1'
#633500
b10001 ?
b10001 (
0-
#635000
b11 >
b10 =
0'
1&
#637500
1'
#638500
b10001 ,
b10001 1
1-
#640000
0'
0&
#642500
1"
b110 <
b101 2
b100 ;
1'
#643500
0-
#645000
b10 >
b110 =
0'
1&
#646000
1)
#647500
1'
#650000
0'
0&
#652500
1'
#655000
b100001 !
b100001 0
b1 8
b10 3
b1 7
b110 >
0'
1&
#656000
0)
#657500
b1 9
1'
#660000
0'
0&
#662500
0"
b1 :
1'
#665000
0'
1&
#667500
1'
#670000
0'
0&
#672500
1'
#675000
0'
1&
#676000
1)
#677500
1'
#680000
0'
0&
#682500
1'
#685000
b1000011 !
b1000011 0
b11 8
b11 3
b10 7
0'
1&
#686000
b110000 ?
b110000 (
0)
#687500
b11 9
1'
#688500
b110000 ,
b110000 1
1-
#690000
0'
0&
#692500
b11 :
0"
b111 <
b110 2
b101 ;
1'
#693500
b10010 ?
b10010 (
0-
#695000
b111 =
0'
1&
#697500
1'
#698500
b10010 ,
b10010 1
1-
#700000
0'
0&
#702500
1"
b101 <
b111 2
b110 ;
1'
#703500
0-
#705000
b111 >
b101 =
0'
1&
#706000
1)
#707500
1'
#710000
0'
0&
#712500
1'
#715000
b10001 !
b10001 0
b10 8
b100 3
b11 7
b101 >
0'
1&
#716000
0)
#717500
b10 9
1'
#720000
0'
0&
#722500
0"
b10 :
1'
#725000
0'
1&
#727500
b1100 ?
b1100 (
1'
#730000
0'
0&
#732500
1'
#733500
b1100 ,
b1100 1
1-
#735000
0'
1&
#737500
1"
b100 <
b0 2
b111 ;
1'
#738500
0-
#740000
0'
0&
#742500
1'
#745000
b100 =
0'
1&
#746000
1)
#747500
1'
#750000
0'
0&
#752500
1'
#755000
b110000 !
b110000 0
b110 8
b101 3
b100 7
b100 >
0'
1&
#756000
0)
#757500
b110 9
1'
#760000
0'
0&
#762500
0"
b110 :
1'
#765000
0'
1&
#767500
1'
#770000
0'
0&
#772500
1'
#775000
0'
1&
#776000
1)
#777500
1'
#780000
0'
0&
#782500
1'
#785000
b10010 !
b10010 0
b111 8
b110 3
b101 7
0'
1&
#786000
0)
#787500
b111 9
1'
#790000
0'
0&
#792500
b111 :
1'
#795000
0'
1&
#796000
1)
#797500
1'
#800000
0'
0&
#802500
1'
#805000
b1100 !
b1100 0
b101 8
b111 3
b110 7
0'
1&
#806000
b1110 ?
b1110 (
0)
#807500
b101 9
1'
#808500
b1110 ,
b1110 1
1-
#810000
0'
0&
#812500
b101 :
b0 <
b1 2
b0 ;
1'
#813500
b1000000 ?
b1000000 (
0-
#815000
b0 =
0'
1&
#817500
1'
#818500
b1000000 ,
b1000000 1
1-
#820000
0'
0&
#822500
b1 <
b10 2
b1 ;
1'
#823500
0-
#825000
b0 >
b1 =
0'
1&
#826000
1)
#827500
1'
#830000
0'
0&
#832500
1'
#835000
b1110 !
b1110 0
b100 8
b0 3
b111 7
b1 >
0'
1&
#836000
b10001 ?
b10001 (
0)
#837500
b100 9
1'
#838500
b10001 ,
b10001 1
1-
#840000
0'
0&
#842500
b100 :
0"
b11 <
b11 2
b10 ;
1'
#843500
b1001001 ?
b1001001 (
0-
#845000
b11 =
0'
1&
#847500
1'
#848500
b1001001 ,
b1001001 1
1-
#850000
0'
0&
#852500
1"
b10 <
b100 2
b11 ;
1'
#853500
b11001 ?
b11001 (
0-
#855000
b11 >
b10 =
0'
1&
#857500
1'
#858500
b11001 ,
b11001 1
1-
#860000
0'
0&
#862500
1'
#863500
b1011110 ?
b1011110 (
0-
#865000
b10 >
0'
1&
#867500
1'
#868500
b1011110 ,
b1011110 1
1-
#870000
0'
0&
#872500
1'
#873500
0-
#875000
0'
1&
#876000
1)
#877500
1'
#880000
0'
0&
#882500
1'
#885000
b1000000 !
b1000000 0
b0 8
b1 3
b0 7
0'
1&
#886000
0)
#887500
b0 9
1'
#890000
0'
0&
#892500
0"
b0 :
1'
#895000
0'
1&
#897500
b1010101 ?
b1010101 (
1'
#900000
0'
0&
#902500
1'
#903500
b1010101 ,
b1010101 1
1-
#905000
0'
1&
#907500
1"
b110 <
b101 2
b100 ;
1'
#908500
0-
#910000
0'
0&
#912500
1'
#915000
b110 =
0'
1&
#916000
1)
#917500
1'
#920000
0'
0&
#922500
1'
#925000
b10001 !
b10001 0
b110 >
b1 8
b10 3
b1 7
0'
1&
#926000
0)
#927500
b1 9
1'
#930000
0'
0&
#932500
0"
b1 :
1'
#935000
0'
1&
#937500
b1001000 ?
b1001000 (
1'
#940000
0'
0&
#942500
1'
#943500
b1001000 ,
b1001000 1
1-
#945000
0'
1&
#947500
1"
b111 <
b110 2
b101 ;
1'
#948500
0-
#950000
0'
0&
#952500
1'
#955000
b111 =
0'
1&
#956000
1)
#957500
1'
#960000
0'
0&
#962500
1'
#965000
b1001001 !
b1001001 0
b111 >
b11 8
b11 3
b10 7
0'
1&
#966000
0)
#967500
b11 9
1'
#970000
0'
0&
#972500
0"
b11 :
1'
#975000
0'
1&
#977500
1'
#980000
0'
0&
#982500
1'
#985000
0'
1&
#986000
1)
#987500
1'
#990000
0'
0&
#992500
1'
#995000
b1010101 !
b1010101 0
b10 8
b100 3
b11 7
0'
1&
#996000
b1010 ?
b1010 (
0)
#997500
b10 9
1'
#998500
b1010 ,
b1010 1
1-
#1000000
0'
0&
#1002500
b10 :
0"
b101 <
b111 2
b110 ;
1'
#1003500
b11100 ?
b11100 (
0-
#1005000
b101 =
0'
1&
#1007500
1'
#1008500
b11100 ,
b11100 1
1-
#1010000
0'
0&
#1012500
1"
b100 <
b0 2
b111 ;
1'
#1013500
0-
#1015000
b101 >
b100 =
0'
1&
#1016000
1)
#1017500
1'
#1020000
0'
0&
#1022500
1'
#1025000
b1001000 !
b1001000 0
b100 >
b110 8
b101 3
b100 7
0'
1&
#1026000
0)
#1027500
b110 9
1'
#1030000
0'
0&
#1032500
0"
b110 :
1'
#1035000
0'
1&
#1037500
1'
#1040000
0'
0&
#1042500
1'
#1045000
0'
1&
#1046000
1)
#1047500
1'
#1050000
0'
0&
#1052500
1'
#1055000
b1010 !
b1010 0
b111 8
b110 3
b101 7
0'
1&
#1056000
0)
#1057500
b111 9
1'
#1060000
0'
0&
#1062500
b111 :
1'
#1065000
0'
1&
#1066000
1)
#1067500
1'
#1070000
0'
0&
#1072500
1'
#1075000
b11100 !
b11100 0
b101 8
b111 3
b110 7
0'
1&
#1076000
0)
#1077500
b101 9
1'
#1080000
0'
0&
#1082500
b101 :
1'
#1085000
0'
1&
#1086000
1)
#1087500
1'
#1090000
0'
0&
#1092500
1'
#1095000
b1010101 !
b1010101 0
1#
b100 8
b0 3
b111 7
0'
1&
#1096000
0)
#1097500
b100 9
1'
#1100000
0'
0&
#1102500
b100 :
1'
#1105000
0'
1&
#1106000
1)
#1107500
1'
#1110000
0'
0&
#1112500
1'
#1115000
0'
1&
#1116000
0)
#1117500
1'
#1120000
0'
0&
#1122500
1'
#1125000
0'
1&
#1126000
1)
#1127500
1'
#1130000
0'
0&
#1132500
1'
#1135000
0'
1&
#1136000
0)
#1137500
1'
#1140000
0'
0&
#1142500
1'
#1145000
0'
1&
#1146000
1)
#1147500
1'
#1150000
0'
0&
#1152500
1'
#1155000
0'
1&
#1156000
0)
#1157500
1'
#1160000
0'
0&
#1162500
1'
#1165000
0'
1&
#1166000
1)
#1167500
1'
#1170000
0'
0&
#1172500
1'
#1175000
0'
1&
#1176000
b101110 ?
b101110 (
0)
#1177500
1'
#1178500
b101110 ,
b101110 1
1-
#1180000
0'
0&
#1182500
b0 <
b1 2
b0 ;
b101110 !
b101110 0
1'
#1183500
0-
#1185000
b0 =
0'
1&
#1186000
1)
#1187500
1'
#1190000
0'
0&
#1192500
1'
#1195000
0#
b0 >
0'
1&
#1196000
0)
#1197500
1'
#1200000
0'
0&
#1202500
1'
#1205000
0'
1&
#1206000
1)
#1207500
1'
#1210000
0'
0&
#1212500
1'
#1215000
b1001000 !
b1001000 0
1#
b0 8
b1 3
b0 7
0'
1&
#1216000
b1001010 ?
b1001010 (
0)
#1217500
b0 9
1'
#1218500
b1001010 ,
b1001010 1
1-
#1220000
0'
0&
#1222500
b0 :
b1 <
b10 2
b1 ;
b1001010 !
b1001010 0
1'
#1223500
0-
#1225000
b1 =
0'
1&
#1226000
1)
#1227500
1'
#1230000
0'
0&
#1232500
1'
#1235000
0#
b1 >
0'
1&
#1236000
0)
#1237500
1'
#1240000
0'
0&
#1242500
1'
#1245000
0'
1&
#1246000
1)
#1247500
1'
#1250000
0'
0&
#1252500
1'
#1255000
b1010 !
b1010 0
1#
b1 8
b10 3
b1 7
0'
1&
#1256000
b1111 ?
b1111 (
0)
#1257500
b1 9
1'
#1258500
b1111 ,
b1111 1
1-
#1260000
0'
0&
#1262500
b1 :
b11 <
b11 2
b10 ;
b1111 !
b1111 0
1'
#1263500
0-
#1265000
b11 =
0'
1&
#1266000
1)
#1267500
1'
#1270000
0'
0&
#1272500
1'
#1275000
0#
b11 >
0'
1&
#1276000
0)
#1277500
1'
#1280000
0'
0&
#1282500
1'
#1285000
0'
1&
#1286000
1)
#1287500
1'
#1290000
0'
0&
#1292500
1'
#1295000
b11100 !
b11100 0
1#
b11 8
b11 3
b10 7
0'
1&
#1296000
0)
#1297500
b11 9
1'
#1300000
0'
0&
#1302500
b11 :
1'
#1305000
0'
1&
#1306000
1)
#1307500
1'
#1310000
0'
0&
#1312500
1'
#1315000
0'
1&
#1316000
0)
#1317500
1'
#1320000
0'
0&
#1322500
1'
#1325000
0'
1&
#1326000
1)
#1327500
1'
#1330000
0'
0&
#1332500
1'
#1335000
0'
1&
#1336000
b1100 ?
b1100 (
0)
#1337500
1'
#1338500
b1100 ,
b1100 1
1-
#1340000
0'
0&
#1342500
b10 <
b100 2
b11 ;
b1100 !
b1100 0
1'
#1343500
b1000111 ?
b1000111 (
0-
#1345000
b10 =
0'
1&
#1347500
1'
#1348500
b1000111 ,
b1000111 1
1-
#1350000
0'
0&
#1352500
b110 <
b101 2
b100 ;
1'
#1353500
b1001010 ?
b1001010 (
0-
#1355000
0#
b10 >
b110 =
0'
1&
#1357500
1'
#1358500
b1001010 ,
b1001010 1
1-
#1360000
0'
0&
#1362500
b111 <
b110 2
b101 ;
1'
#1363500
0-
#1365000
b110 >
b111 =
0'
1&
#1366000
1)
#1367500
1'
#1370000
0'
0&
#1372500
1'
#1375000
b1000111 !
b1000111 0
b10 8
b100 3
b11 7
b111 >
0'
1&
#1376000
b1001111 ?
b1001111 (
0)
#1377500
b10 9
1'
#1378500
b1001111 ,
b1001111 1
1-
#1380000
0'
0&
#1382500
b10 :
0"
b101 <
b111 2
b110 ;
1'
#1383500
0-
#1385000
b101 =
0'
1&
#1386000
1)
#1387500
1'
#1390000
0'
0&
#1392500
1'
#1395000
b1001010 !
b1001010 0
b110 8
b101 3
b100 7
b101 >
0'
1&
#1396000
0)
